__init__.py
pdbfixer/__init__.py
pdbfixer/pdbfixer.py
pdbfixer/ui.py
pdbfixer/uiserver.py
pdbfixer/tests/__init__.py
pdbfixer/tests/test_add_hydrogens.py
pdbfixer/tests/test_build_and_simulate.py
pdbfixer/tests/test_charge_and_solvate.py
pdbfixer/tests/test_cli.py
pdbfixer/tests/test_mutate.py
pdbfixer/tests/test_removechains.py
black_pdbfixer-1.9.0.dist-info/LICENSE
black_pdbfixer-1.9.0.dist-info/METADATA
black_pdbfixer-1.9.0.dist-info/WHEEL
black_pdbfixer-1.9.0.dist-info/top_level.txt
black_pdbfixer-1.9.0.dist-info/RECORD
