Metadata-Version: 2.1
Name: black-pdbfixer
Version: 1.9.0
Summary: Fork of pdbfixer (https://github.com/openmm/pdbfixer) to be able to pip install it.
Author: Peter Eastman
Author-email: "Julian M. Kleber" <julian.m.kleber@gmail.com>
Project-URL: Homepage, https://www.codeberg.org/cap_jmk/pdfixer.git
Project-URL: Bug Tracker, https://www.codeberg.org/cap_jmk/pdbfixer.git/issues
Classifier: Programming Language :: Python :: 3
Classifier: License :: OSI Approved :: GNU General Public License v3 (GPLv3)
Classifier: Operating System :: OS Independent
Requires-Python: >=3.8
License-File: LICENSE
Requires-Dist: numpy <2
Requires-Dist: openmm >=7.1
